scf_add/__init__.py
scf_add/__version__.py
scf_add/command.py
scf_add/utils.py
scf_add-0.1.dist-info/DESCRIPTION.rst
scf_add-0.1.dist-info/METADATA
scf_add-0.1.dist-info/RECORD
scf_add-0.1.dist-info/WHEEL
scf_add-0.1.dist-info/entry_points.txt
scf_add-0.1.dist-info/metadata.json
scf_add-0.1.dist-info/top_level.txt
